setup.py
mygrate/__init__.py
mygrate/binlog.py
mygrate/callbacks.py
mygrate/config.py
mygrate/daemon.py
mygrate/exceptions.py
mygrate/query.py
mygrate.egg-info/PKG-INFO
mygrate.egg-info/SOURCES.txt
mygrate.egg-info/dependency_links.txt
mygrate.egg-info/entry_points.txt
mygrate.egg-info/requires.txt
mygrate.egg-info/top_level.txt
test/test_binlog.py
test/test_query.py