Metadata-Version: 1.1
Name: mygrate
Version: 0.7
Summary: Facilitates the migration of data from MySQL or MariaDB with no downtime.
Home-page: https://github.com/icgood/mygrate
Author: Ian Good
Author-email: ian.good@rackspace.com
License: MIT
Platform: UNKNOWN
Classifier: Development Status :: 3 - Alpha
Classifier: Intended Audience :: Developers
Classifier: Intended Audience :: Information Technology
Classifier: License :: OSI Approved :: MIT License
Classifier: Programming Language :: Python
